SigVarGen/__init__.py
SigVarGen/config.py
SigVarGen/config_hardcoded.py
SigVarGen/utils.py
SigVarGen/noise/__init__.py
SigVarGen/noise/envelopes.py
SigVarGen/noise/noise.py
SigVarGen/signal/__init__.py
SigVarGen/signal/periodic_interrupts.py
SigVarGen/signal/response_signals.py
SigVarGen/signal/signal_generation.py
SigVarGen/variations/__init__.py
SigVarGen/variations/baseline_drift.py
SigVarGen/variations/transformations.py
SigVarGen/variations/variations.py
sigvargen-1.1.1.dist-info/licenses/LICENSE
sigvargen-1.1.1.dist-info/METADATA
sigvargen-1.1.1.dist-info/WHEEL
sigvargen-1.1.1.dist-info/top_level.txt
sigvargen-1.1.1.dist-info/RECORD
