Metadata-Version: 2.4
Name: SigVarGen
Version: 1.1.1
Summary: Python framework designed to create multiple variants of an idle-state signals and signals affected by external perturbations under the same environmental conditions.
Author-email: SigVarGen developers <ovakulenko@uwaterloo.ca>
Project-URL: Homepage, https://github.com/SigVarGen/SigVarGen
Project-URL: Issues, https://github.com/SigVarGen/SigVarGen/issues
Classifier: Programming Language :: Python :: 3
Classifier: License :: OSI Approved :: MIT License
Classifier: Operating System :: OS Independent
Requires-Python: >=3.8
License-File: LICENSE
Requires-Dist: numpy>=1.24.3
Requires-Dist: scipy>=1.11.0
Requires-Dist: pytest>=8.3.5
Dynamic: license-file
